dagster_qdrant/__init__.py
dagster_qdrant/config.py
dagster_qdrant/resource.py
dagster_qdrant-0.0.3.dist-info/METADATA
dagster_qdrant-0.0.3.dist-info/WHEEL
dagster_qdrant-0.0.3.dist-info/top_level.txt
dagster_qdrant-0.0.3.dist-info/RECORD
