Metadata-Version: 2.4
Name: dagster-qdrant
Version: 0.0.3
Summary: Dagster integration with Qdrant
Requires-Python: >=3.10
Requires-Dist: dagster>=1.8.0
Requires-Dist: qdrant-client>=1.13.2
